{
  "count": 2,
  "next": null,
  "previous": null,
  "results": [
    {
      "url": "https://unity.unitedlayer.com/rest/terminalservermodel/1/",
      "id": 1,
      "name": "2611XM",
      "num_ports": 24,
      "manufacturer": {
        "url": "https://unity.unitedlayer.com/rest/manufacturer/13/",
        "id": 13,
        "name": "cisco"
      }
    },
    {
      "url": "https://unity.unitedlayer.com/rest/terminalservermodel/4/",
      "id": 4,
      "name": "2611",
      "num_ports": null,
      "manufacturer": {
        "url": "https://unity.unitedlayer.com/rest/manufacturer/13/",
        "id": 13,
        "name": "cisco"
      }
    }
  ]
}