[
  {
    "url": "http://localhost:3001/rest/voltagetype/1/",
    "id": 1,
    "voltage_type": "48V"
  },
  {
    "url": "http://localhost:3001/rest/voltagetype/2/",
    "id": 2,
    "voltage_type": "120V"
  },
  {
    "url": "http://localhost:3001/rest/voltagetype/3/",
    "id": 3,
    "voltage_type": "208V"
  },
  {
    "url": "http://localhost:3001/rest/voltagetype/4/",
    "id": 4,
    "voltage_type": "50V"
  },
  {
    "url": "http://localhost:3001/rest/voltagetype/5/",
    "id": 5,
    "voltage_type": "110V"
  },
  {
    "url": "http://localhost:3001/rest/voltagetype/6/",
    "id": 6,
    "voltage_type": "160V"
  },
  {
    "url": "http://localhost:3001/rest/voltagetype/7/",
    "id": 7,
    "voltage_type": "180V"
  },
  {
    "url": "http://localhost:3001/rest/voltagetype/8/",
    "id": 8,
    "voltage_type": "220V"
  },
  {
    "url": "http://localhost:3001/rest/voltagetype/9/",
    "id": 9,
    "voltage_type": "240V"
  }
]
